pudgetool/__init__.py
pudgetool/entry_point.py
pudgetool/main.py
pudgetool/jump/__init__.py
pudgetool/jump/command.py
pudgetool/lzbench/__init__.py
pudgetool/lzbench/command.py
pudgetool/s3/__init__.py
pudgetool/s3/command.py
pudgetool/s3/main.py
pudgetool/s3/utils.py
pudgetool-1.0.3.dist-info/LICENSE
pudgetool-1.0.3.dist-info/METADATA
pudgetool-1.0.3.dist-info/WHEEL
pudgetool-1.0.3.dist-info/entry_points.txt
pudgetool-1.0.3.dist-info/top_level.txt
pudgetool-1.0.3.dist-info/RECORD
